{
	"time": {{ site.time | jsonify }},
	"cloudcannon": {
		"name": "cloudcannon-jekyll",
		"version": {{ gem_version | jsonify }}
	},
	"generator": {
		"name": "jekyll",
		"version": {{ jekyll.version | jsonify }},
		"environment": {{ jekyll.env | jsonify }},
		"metadata": {
			"markdown": {{ site.markdown | cc_safe_jsonify }},
			"kramdown": {{ site.kramdown | cc_safe_jsonify }},
			"commonmark": {{ site.commonmark | cc_safe_jsonify }}
		}
	},{% if site.cloudcannon.data %}
	"data": {{ site.data | cc_safe_jsonify }},{% endif %}
	"collections": {
		"posts": {{ site.posts | reverse | cc_safe_jsonify }},
		{% for collection in site.collections %}"{{ collection[0] | xml_escape }}": {{ collection[1].docs | cc_safe_jsonify }}{% unless forloop.last %},{% endunless %}
		{% endfor %}
	},
	"pages": {{ site.pages | cc_safe_jsonify }},
	"static": {{ site.static_files | cc_static_files_jsonify }}
}
